{
  "generated_at": "2026-02-24T20:14:49.797Z",
  "packages": {
    "docx-core": {
      "lines": 88.39,
      "branches": 80.16,
      "functions": 88.68,
      "statements": 88.39,
      "deltas": {
        "lines": null,
        "branches": null,
        "functions": null,
        "statements": null
      }
    },
    "docx-mcp": {
      "lines": 86.65,
      "branches": 78.85,
      "functions": 93.4,
      "statements": 86.65,
      "deltas": {
        "lines": null,
        "branches": null,
        "functions": null,
        "statements": null
      }
    }
  },
  "aggregate": {
    "lines_mean": 87.52,
    "branches_mean": 79.5,
    "functions_mean": 91.04,
    "statements_mean": 87.52
  }
}
